__init__.py
easylogger.py
elogger-0.1.2.dist-info/RECORD
elogger-0.1.2.dist-info/metadata.json
elogger-0.1.2.dist-info/WHEEL
elogger-0.1.2.dist-info/DESCRIPTION.rst
elogger-0.1.2.dist-info/top_level.txt
elogger-0.1.2.dist-info/METADATA
easylogger/__init__.py
