Metadata-Version: 2.0
Name: elogger
Version: 0.1.2
Summary: easylogger for easyspider
Home-page: UNKNOWN
Author: zhang1Tian
Author-email: hhczy1003@gmail.com
License: MIT License
Keywords: log,logger
Platform: any
